MANIFEST.in
README.md
setup.cfg
setup.py
pythonparser/__init__.py
pythonparser/__main__.py
pythonparser/algorithm.py
pythonparser/ast.py
pythonparser/diagnostic.py
pythonparser/lexer.py
pythonparser/parser.py
pythonparser/source.py
pythonparser.egg-info/PKG-INFO
pythonparser.egg-info/SOURCES.txt
pythonparser.egg-info/dependency_links.txt
pythonparser.egg-info/namespace_packages.txt
pythonparser.egg-info/requires.txt
pythonparser.egg-info/top_level.txt
pythonparser/coverage/__init__.py
pythonparser/coverage/parser.py
pythonparser/test/__init__.py
pythonparser/test/test_algorithm.py
pythonparser/test/test_diagnostic.py
pythonparser/test/test_lexer.py
pythonparser/test/test_parser.py
pythonparser/test/test_source.py
pythonparser/test/test_utils.py