Metadata-Version: 1.1
Name: pythonparser
Version: 1.2
Summary: A Python parser intended for use in tooling
Home-page: https://m-labs.hk/pythonparser
Author: whitequark
Author-email: whitequark@whitequark.org
License: MIT
Download-URL: https://github.com/m-labs/pythonparser
Platform: UNKNOWN
